Metadata-Version: 2.1
Name: findi-descent
Version: 0.1.0
Summary: FinDi: Finite Difference Gradient Descent can optimize any function, including the ones without analytic form, by employing finite difference numerical differentiation within a gradient descent algorithm.
Home-page: https://github.com/draktr/findi-descent
Author: draktr
License: MIT License
Project-URL: Documentation, https://findi-descent.readthedocs.io/en/latest/
Project-URL: Issues, https://github.com/draktr/findi-descent/issues
Keywords: optimization,gradient-descent,numerical-analysis,numerical-differentiation
Classifier: Development Status :: 4 - Beta
Classifier: Intended Audience :: Education
Classifier: Intended Audience :: Financial and Insurance Industry
Classifier: Intended Audience :: Healthcare Industry
Classifier: Intended Audience :: Manufacturing
Classifier: Intended Audience :: Science/Research
Classifier: License :: OSI Approved :: MIT License
Classifier: Operating System :: OS Independent
Classifier: Programming Language :: Python
Classifier: Topic :: Scientific/Engineering
Classifier: Topic :: Scientific/Engineering :: Artificial Intelligence
Classifier: Topic :: Scientific/Engineering :: Astronomy
Classifier: Topic :: Scientific/Engineering :: Atmospheric Science
Classifier: Topic :: Scientific/Engineering :: Bio-Informatics
Classifier: Topic :: Scientific/Engineering :: Chemistry
Classifier: Topic :: Scientific/Engineering :: Mathematics
Classifier: Topic :: Scientific/Engineering :: Physics
Requires-Python: >=3.8
License-File: LICENSE
